flask_cloudwatch_metric/__init__.py
flask_cloudwatch_metric/decorator/__init__.py
flask_cloudwatch_metric-0.1.7.dist-info/LICENSE
flask_cloudwatch_metric-0.1.7.dist-info/METADATA
flask_cloudwatch_metric-0.1.7.dist-info/WHEEL
flask_cloudwatch_metric-0.1.7.dist-info/top_level.txt
flask_cloudwatch_metric-0.1.7.dist-info/RECORD
