Metadata-Version: 2.1
Name: flask-cloudwatch-metric
Version: 0.1.7
Summary: A Flask extension to provide easy integration with CloudWatch to publish metrics
Home-page: https://github.com/yxiao1996/flask-cloudwatch-metric
Author: Yu Xiao
Author-email: yxiao96@bu.edu
License: MIT
Keywords: flask,cloudwatch,metrics,monitoring
Platform: any
Classifier: Development Status :: 2 - Pre-Alpha
Classifier: Intended Audience :: Developers
Classifier: Intended Audience :: System Administrators
Classifier: Topic :: System :: Monitoring
Classifier: License :: OSI Approved :: MIT License
Classifier: Programming Language :: Python :: 3.8
License-File: LICENSE
Requires-Dist: Flask
Requires-Dist: boto3
